mapd/__init__.py
mapd/classifiers/__init__.py
mapd/classifiers/make_mapd_classifier.py
mapd/classifiers/make_predictions.py
mapd/classifiers/utils/__init__.py
mapd/classifiers/utils/create_sklearn_matrix.py
mapd/mapd_module.py
mapd/probes/__init__.py
mapd/probes/make_probe_suites.py
mapd/probes/probe_suite_generator.py
mapd/probes/utils/__init__.py
mapd/probes/utils/idx_dataset.py
mapd/probes/utils/loss_dataset.py
mapd/proxies/__init__.py
mapd/proxies/data_wrapper.py
mapd/proxies/proxy_calculator.py
mapd/utils/__init__.py
mapd/utils/make_dataloaders.py
mapd/utils/wrap_dataset.py
mapd/visualization/__init__.py
mapd/visualization/surface_predictions.py
mapd/visualization/visualization_example.py
mapd/visualization/visualization_tool.py
mapd-0.1.0.dist-info/LICENSE
mapd-0.1.0.dist-info/METADATA
mapd-0.1.0.dist-info/WHEEL
mapd-0.1.0.dist-info/RECORD
